{
    "signature": {
        "source": "NASA/JPL SBDB Close Approach Data API",
        "version": "1.4"
    },
    "count": "5",
    "fields": [
        "des",
        "orbit_id",
        "jd",
        "cd",
        "dist",
        "dist_min",
        "dist_max",
        "v_rel",
        "v_inf",
        "t_sigma_f",
        "h",
        "diameter",
        "diameter_sigma",
        "fullname"
    ],
    "data": [
        [
            "2020 AP1",
            "2",
            "2458850.410061365",
            "2020-Jan-01 21:50",
            "0.0018292029491533",
            "0.00182349400329298",
            "0.00183491318579067",
            "5.46781980927713",
            "5.46454208151903",
            "00:03",
            "29.6",
            null,
            null,
            "        (2020 AP1)"
        ],
        [
            "2020 AD",
            "3",
            "2458850.883299555",
            "2020-Jan-02 09:12",
            "0.00761998436603393",
            "0.0076107171486378",
            "0.0076292527627401",
            "16.5219316045998",
            "16.5216712847429",
            "< 00:01",
            "27.2",
            null,
            null,
            "        (2020 AD)"
        ],
        [
            "2020 AC",
            "7",
            "2458851.341295617",
            "2020-Jan-02 20:11",
            "0.00703159254464239",
            "0.0070246841016683",
            "0.00703850223436277",
            "6.31339362726432",
            "6.31265533621147",
            "< 00:01",
            "26.7",
            null,
            null,
            "        (2020 AC)"
        ],
        [
            "2020 AC1",
            "7",
            "2458852.160823127",
            "2020-Jan-03 15:52",
            "0.0073235235302349",
            "0.00730867480161816",
            "0.00733837321235666",
            "5.6317494714205",
            "5.63095480290034",
            "00:03",
            "28.4",
            null,
            null,
            "        (2020 AC1)"
        ],
        [
            "2020 AN1",
            "6",
            "2458852.654152125",
            "2020-Jan-04 03:42",
            "0.00475277571584338",
            "0.00474555894173411",
            "0.00475999337282462",
            "10.9325590734685",
            "10.9319283163633",
            "< 00:01",
            "26.0",
            null,
            null,
            "        (2020 AN1)"
        ]
    ]
}